src/__init__.py
src/example.py
src/nester.py
src/nester/nester.py
src/nester/setup.py
nester_monstrosity878-1.3.0.dist-info/METADATA
nester_monstrosity878-1.3.0.dist-info/WHEEL
nester_monstrosity878-1.3.0.dist-info/entry_points.txt
nester_monstrosity878-1.3.0.dist-info/license_files/LICENSE.txt
nester_monstrosity878-1.3.0.dist-info/RECORD
