Metadata-Version: 2.1
Name: nester-monstrosity878
Version: 1.3.0
Summary: Used for printing nested python lists either by indentation or without
Project-URL: Bug Tracker, https://github.com/pypa/sampleproject/issues
Project-URL: Homepage, https://github.com/pypa/sampleproject
Author-email: ObscureIT <akif.khan1704@gmail.com>
Classifier: License :: OSI Approved :: MIT License
Classifier: Operating System :: OS Independent
Classifier: Programming Language :: Python :: 3
Requires-Python: >=3.7
